{
  "resourceType" : "ValueSet",
  "id" : "PCTSupportingInfoTypeVS",
  "text" : {
    "status" : "generated",
    "div" : "<div xmlns=\"http://www.w3.org/1999/xhtml\"><p class=\"res-header-id\"><b>Generated Narrative: ValueSet PCTSupportingInfoTypeVS</b></p><a name=\"PCTSupportingInfoTypeVS\"> </a><a name=\"hcPCTSupportingInfoTypeVS\"> </a><a name=\"PCTSupportingInfoTypeVS-en-US\"> </a><ul><li>Include all codes defined in <a href=\"CodeSystem-PCTSupportingInfoType.html\"><code>http://hl7.org/fhir/us/davinci-pct/CodeSystem/PCTSupportingInfoType</code></a></li></ul></div>"
  },
  "extension" : [{
    "url" : "http://hl7.org/fhir/StructureDefinition/structuredefinition-wg",
    "valueCode" : "fm"
  },
  {
    "url" : "http://hl7.org/fhir/StructureDefinition/structuredefinition-standards-status",
    "valueCode" : "trial-use",
    "_valueCode" : {
      "extension" : [{
        "url" : "http://hl7.org/fhir/StructureDefinition/structuredefinition-conformance-derivedFrom",
        "valueCanonical" : "http://hl7.org/fhir/us/davinci-pct/ImplementationGuide/hl7.fhir.us.davinci-pct"
      }]
    }
  }],
  "url" : "http://hl7.org/fhir/us/davinci-pct/ValueSet/PCTSupportingInfoTypeVS",
  "identifier" : [{
    "system" : "urn:ietf:rfc:3986",
    "value" : "urn:oid:2.16.840.1.113883.4.642.40.4.48.33"
  }],
  "version" : "2.0.0-draft",
  "name" : "PCTSupportingInfoTypeVS",
  "title" : "PCT Supporting Info Type Value Set",
  "status" : "active",
  "experimental" : false,
  "date" : "2025-06-03T13:32:08+00:00",
  "publisher" : "HL7 International / Financial Management",
  "contact" : [{
    "name" : "HL7 International / Financial Management",
    "telecom" : [{
      "system" : "url",
      "value" : "http://www.hl7.org/Special/committees/fm"
    },
    {
      "system" : "email",
      "value" : "fmlists@lists.hl7.org"
    }]
  }],
  "description" : "Codes to specify the type of the supplied supporting information",
  "jurisdiction" : [{
    "coding" : [{
      "system" : "urn:iso:std:iso:3166",
      "code" : "US"
    }]
  }],
  "copyright" : "This Valueset is not copyrighted.",
  "compose" : {
    "include" : [{
      "system" : "http://hl7.org/fhir/us/davinci-pct/CodeSystem/PCTSupportingInfoType"
    }]
  }
}